librenms_handler/__init__.py
librenms_handler/librenms.py
librenms_handler/arp/__init__.py
librenms_handler/arp/arp.py
librenms_handler/device_groups/__init__.py
librenms_handler/device_groups/device_groups.py
librenms_handler/devices/__init__.py
librenms_handler/devices/devices.py
librenms_handler/inventory/__init__.py
librenms_handler/inventory/inventory.py
librenms_handler/locations/__init__.py
librenms_handler/locations/locations.py
librenms_handler/logs/__init__.py
librenms_handler/logs/logs.py
librenms_handler/switching/__init__.py
librenms_handler/switching/switching.py
librenms_handler/system/__init__.py
librenms_handler/system/system.py
librenms_handler-0.4.3.dist-info/LICENSE.txt
librenms_handler-0.4.3.dist-info/METADATA
librenms_handler-0.4.3.dist-info/WHEEL
librenms_handler-0.4.3.dist-info/top_level.txt
librenms_handler-0.4.3.dist-info/RECORD
