Metadata-Version: 2.1
Name: librenms-handler
Version: 0.4.3
Summary: A Python library to interact with the LibreNMS API (v0)
Author-email: James Whale <james@james-whale.com>
Project-URL: Homepage, https://github.com/WhaleJ84/librenms_handler
Project-URL: Bug Tracker, https://github.com/WhaleJ84/librenms_handler/issues
Classifier: Programming Language :: Python :: 3
Classifier: License :: OSI Approved :: MIT License
Requires-Python: >=3.6
License-File: LICENSE.txt
Requires-Dist: requests
